flowmason_core/__init__.py
flowmason_core/api.py
flowmason_core/cli/__init__.py
flowmason_core/cli/main.py
flowmason_core/cli/main.py.backup
flowmason_core/cli/commands/__init__.py
flowmason_core/cli/commands/auth.py
flowmason_core/cli/commands/deploy.py
flowmason_core/cli/commands/diff.py
flowmason_core/cli/commands/init.py
flowmason_core/cli/commands/install.py
flowmason_core/cli/commands/mcp.py
flowmason_core/cli/commands/nl.py
flowmason_core/cli/commands/org.py
flowmason_core/cli/commands/pack.py
flowmason_core/cli/commands/pull.py
flowmason_core/cli/commands/registry.py
flowmason_core/cli/commands/run.py
flowmason_core/cli/commands/sf.py
flowmason_core/cli/commands/studio.py
flowmason_core/cli/commands/validate.py
flowmason_core/config/__init__.py
flowmason_core/config/input_mapper.py
flowmason_core/config/installation.py
flowmason_core/config/schema_validator.py
flowmason_core/config/template_resolver.py
flowmason_core/config/type_coercion.py
flowmason_core/config/types.py
flowmason_core/copilot/__init__.py
flowmason_core/copilot/context.py
flowmason_core/copilot/prompts.py
flowmason_core/copilot/service.py
flowmason_core/core/__init__.py
flowmason_core/core/decorators.py
flowmason_core/core/types.py
flowmason_core/diff/__init__.py
flowmason_core/diff/formatter.py
flowmason_core/diff/merge.py
flowmason_core/diff/pipeline_diff.py
flowmason_core/execution/__init__.py
flowmason_core/execution/cancellation.py
flowmason_core/execution/control_flow_handler.py
flowmason_core/execution/retry.py
flowmason_core/execution/types.py
flowmason_core/execution/universal_executor.py
flowmason_core/federation/__init__.py
flowmason_core/federation/coordinator.py
flowmason_core/federation/data_router.py
flowmason_core/federation/models.py
flowmason_core/federation/remote_executor.py
flowmason_core/inheritance/__init__.py
flowmason_core/inheritance/merger.py
flowmason_core/inheritance/resolver.py
flowmason_core/inheritance/validator.py
flowmason_core/kubernetes/__init__.py
flowmason-1.0.21.dist-info/METADATA
flowmason-1.0.21.dist-info/WHEEL
flowmason-1.0.21.dist-info/entry_points.txt
flowmason-1.0.21.dist-info/licenses/LICENSE
flowmason-1.0.21.dist-info/RECORD
