Metadata-Version: 2.4
Name: flowmason
Version: 1.0.21
Summary: Universal AI Workflow Infrastructure - Build, debug, and deploy intelligent pipelines
Project-URL: Homepage, https://flowmason.com
Project-URL: Documentation, https://flowmason.com/docs
Project-URL: Support, https://flowmason.com/support
Author-email: FlowMason <support@flowmason.com>
License-Expression: LicenseRef-Proprietary
License-File: LICENSE
Keywords: agents,ai,automation,llm,orchestration,pipeline,workflow
Classifier: Development Status :: 5 - Production/Stable
Classifier: Intended Audience :: Developers
Classifier: License :: Other/Proprietary License
Classifier: Operating System :: OS Independent
Classifier: Programming Language :: Python :: 3.11
Classifier: Programming Language :: Python :: 3.12
Classifier: Topic :: Scientific/Engineering :: Artificial Intelligence
Classifier: Topic :: Software Development :: Libraries :: Python Modules
Requires-Python: >=3.11
Requires-Dist: fastapi>=0.109.0
Requires-Dist: httpx>=0.26.0
Requires-Dist: pydantic>=2.0.0
Requires-Dist: python-multipart>=0.0.6
Requires-Dist: rich>=13.0.0
Requires-Dist: typer>=0.9.0
Requires-Dist: uvicorn[standard]>=0.27.0
Provides-Extra: all
Requires-Dist: cryptography>=41.0.0; extra == 'all'
Requires-Dist: mcp>=1.0.0; extra == 'all'
Provides-Extra: dev
Requires-Dist: httpx>=0.26.0; extra == 'dev'
Requires-Dist: mypy>=1.0.0; extra == 'dev'
Requires-Dist: pytest-asyncio>=0.21.0; extra == 'dev'
Requires-Dist: pytest-cov>=4.0.0; extra == 'dev'
Requires-Dist: pytest>=7.0.0; extra == 'dev'
Requires-Dist: ruff>=0.1.0; extra == 'dev'
Provides-Extra: mcp
Requires-Dist: mcp>=1.0.0; extra == 'mcp'
Provides-Extra: secrets
Requires-Dist: cryptography>=41.0.0; extra == 'secrets'
